Metadata-Version: 1.0
Name: tsetlinmachinecuda
Version: 0.1.8
Summary: Massively Parallel and Asynchronous Architecture for Logic-based AI.
Home-page: https://github.com/cair/tsetlinmachinecuda/
Author: Ole-Christoffer Granmo
Author-email: ole.granmo@uia.no
License: MIT
Keywords: pattern-recognition cuda machine-learning interpretable-machine-learning rule-based-machine-learning propositional-logic tsetlin-machine regression convolution classification multi-layer
Platform: UNKNOWN
